ShiyanlouPerlJiaochengHeji20160904/README.md
ShiyanlouPerlJiaochengHeji20160904/__init__.py
ShiyanlouPerlJiaochengHeji20160904/__main__.py
ShiyanlouPerlJiaochengHeji20160904/file.epub
ShiyanlouPerlJiaochengHeji20160904/index.html
ShiyanlouPerlJiaochengHeji20160904/css/__init__.py
ShiyanlouPerlJiaochengHeji20160904/css/annotations.css
ShiyanlouPerlJiaochengHeji20160904/css/main.css
ShiyanlouPerlJiaochengHeji20160904/css/normalize.css
ShiyanlouPerlJiaochengHeji20160904/css/popup.css
ShiyanlouPerlJiaochengHeji20160904/font/__init__.py
ShiyanlouPerlJiaochengHeji20160904/font/fontello.eot
ShiyanlouPerlJiaochengHeji20160904/font/fontello.svg
ShiyanlouPerlJiaochengHeji20160904/font/fontello.ttf
ShiyanlouPerlJiaochengHeji20160904/font/fontello.woff
ShiyanlouPerlJiaochengHeji20160904/img/__init__.py
ShiyanlouPerlJiaochengHeji20160904/img/annotator-glyph-sprite.png
ShiyanlouPerlJiaochengHeji20160904/img/annotator-icon-sprite.png
ShiyanlouPerlJiaochengHeji20160904/img/apple-touch-icon.png
ShiyanlouPerlJiaochengHeji20160904/img/cancelfullscreen.png
ShiyanlouPerlJiaochengHeji20160904/img/close.png
ShiyanlouPerlJiaochengHeji20160904/img/fullscreen.png
ShiyanlouPerlJiaochengHeji20160904/img/loader.gif
ShiyanlouPerlJiaochengHeji20160904/img/menu-icon.png
ShiyanlouPerlJiaochengHeji20160904/img/save.png
ShiyanlouPerlJiaochengHeji20160904/img/saved.png
ShiyanlouPerlJiaochengHeji20160904/img/settings-s.png
ShiyanlouPerlJiaochengHeji20160904/img/settings.png
ShiyanlouPerlJiaochengHeji20160904/img/star.png
ShiyanlouPerlJiaochengHeji20160904/js/__init__.py
ShiyanlouPerlJiaochengHeji20160904/js/epub.js
ShiyanlouPerlJiaochengHeji20160904/js/epub.min.js
ShiyanlouPerlJiaochengHeji20160904/js/epub.min.map
ShiyanlouPerlJiaochengHeji20160904/js/hooks.min.js
ShiyanlouPerlJiaochengHeji20160904/js/hooks.min.map
ShiyanlouPerlJiaochengHeji20160904/js/reader.js
ShiyanlouPerlJiaochengHeji20160904/js/reader.js.map
ShiyanlouPerlJiaochengHeji20160904/js/reader.min.js
shiyanlou_perl_jiaocheng_heji_20160904-2024.3.2.0.dist-info/METADATA
shiyanlou_perl_jiaocheng_heji_20160904-2024.3.2.0.dist-info/WHEEL
shiyanlou_perl_jiaocheng_heji_20160904-2024.3.2.0.dist-info/entry_points.txt
shiyanlou_perl_jiaocheng_heji_20160904-2024.3.2.0.dist-info/top_level.txt
shiyanlou_perl_jiaocheng_heji_20160904-2024.3.2.0.dist-info/RECORD
